setup.cfg
setup.py
pdpy/__init__.py
pdpy/combine.py
pdpy/constants.py
pdpy/core.py
pdpy/elections.py
pdpy/errors.py
pdpy/filter.py
pdpy/lords.py
pdpy/members.py
pdpy/mps.py
pdpy/settings.py
pdpy/utils.py
pdpy.egg-info/PKG-INFO
pdpy.egg-info/SOURCES.txt
pdpy.egg-info/dependency_links.txt
pdpy.egg-info/requires.txt
pdpy.egg-info/top_level.txt