Metadata-Version: 1.1
Name: pdpy
Version: 0.1.4
Summary: A package for downloading data from the Parliamentary Data Platform
Home-page: https://github.com/olihawkins/pdpy
Author: Oliver Hawkins
Author-email: oli@olihawkins.com
License: BSD
Download-URL: https://github.com/olihawkins/pdpy/tarball/0.1.4
Keywords: Parliament,MP,House of Commons,House of Lords
Platform: UNKNOWN
